onegov.intranet-0.0.3-py3.4-nspkg.pth
onegov/intranet/.gitignore
onegov/intranet/__init__.py
onegov/intranet/app.py
onegov/intranet/security.py
onegov/intranet/upgrade.py
onegov/intranet/tests/conftest.py
onegov/intranet/tests/test_views.py
onegov/intranet/views/__init__.py
onegov/intranet/views/exceptionviews.py
onegov.intranet-0.0.3.dist-info/DESCRIPTION.rst
onegov.intranet-0.0.3.dist-info/METADATA
onegov.intranet-0.0.3.dist-info/RECORD
onegov.intranet-0.0.3.dist-info/WHEEL
onegov.intranet-0.0.3.dist-info/entry_points.txt
onegov.intranet-0.0.3.dist-info/metadata.json
onegov.intranet-0.0.3.dist-info/namespace_packages.txt
onegov.intranet-0.0.3.dist-info/top_level.txt
