Metadata-Version: 2.0
Name: onegov.intranet
Version: 0.0.3
Summary: Adapts onegov.org for use as an intranet application.
Home-page: http://github.com/OneGov/onegov.intranet
Author: Seantis GmbH
Author-email: info@seantis.ch
License: GPLv2
Platform: any
Classifier: Intended Audience :: Developers
Classifier: Programming Language :: Python :: 3 :: Only
Classifier: Programming Language :: Python :: 3.4
Classifier: Programming Language :: Python :: 3.5
Classifier: Topic :: Software Development :: Libraries :: Python Modules
Classifier: License :: OSI Approved :: GNU General Public License v2 (GPLv2)
Requires-Dist: onegov.core
Requires-Dist: onegov.org
Provides-Extra: test
Requires-Dist: coverage; extra == 'test'
Requires-Dist: onegov-testing; extra == 'test'
Requires-Dist: pytest; extra == 'test'
